Metadata-Version: 2.1
Name: django3-oidc-provider
Version: 0.7.4
Summary: OpenID Connect Provider implementation for Django3.
Home-page: http://github.com/nickoarg/django-oidc-provider
Author: Nicolas Barberis
Author-email: nbarberis@gestionamas.com.ar
License: MIT License
Platform: UNKNOWN
Classifier: Development Status :: 5 - Production/Stable
Classifier: Environment :: Web Environment
Classifier: Framework :: Django
Classifier: Intended Audience :: Developers
Classifier: License :: OSI Approved :: MIT License
Classifier: Operating System :: OS Independent
Classifier: Programming Language :: Python
Classifier: Programming Language :: Python :: 3.7
Classifier: Topic :: Internet :: WWW/HTTP
Classifier: Topic :: Internet :: WWW/HTTP :: Dynamic Content
Requires-Dist: pyjwkest (>=1.3.0)
